<?xml version="1.0" encoding="UTF-8"?><magicdraw><literalunlimitednatural classType="LiteralUnlimitedNatural" humanType="Literal Unlimited Natural" icon="MTConnect SysML Model_files/icon_literalunlimitednatural_2032269321.png" id="_19_0_3_68e0225_1611741204318_738860_24"><documentation humanName="Documentation"/><name humanName="Name"/><owner classType="Property" humanName="Owner" humanType="Reference Property" icon="MTConnect SysML Model_files/icon_referenceproperty_985247931.png" mode="e" name="hasToolLife" refid="EAID_dst8C9154_3651_4af3_9311_2AA3D0EF7282"/><owningUpper classType="Property" humanName="Owning Upper" humanType="Reference Property" icon="MTConnect SysML Model_files/icon_referenceproperty_985247931.png" name="hasToolLife" refid="EAID_dst8C9154_3651_4af3_9311_2AA3D0EF7282"/><qualifiedName humanName="Qualified Name">Assets::CuttingTool::CuttingToolLifeCycle::CuttingToolLifeCycle::hasToolLife::</qualifiedName><text humanName="Text" mode="standard">3</text><TO_DO humanName="To Do"/><TYPE_MODIFIER humanName="Type Modifier"/><value humanName="Value" mode="s,e">3</value><visibility humanName="Visibility">public</visibility></literalunlimitednatural></magicdraw>