<?xml version="1.0" encoding="UTF-8"?><magicdraw><slot classType="Slot" humanType="Slot" icon="MTConnect SysML Model_files/icon_slot_790986191.png" id="_19_0_3_68e0225_1612555979835_70772_44652"><definingFeature classType="Property" humanName="Defining Feature" humanType="Property" icon="MTConnect SysML Model_files/icon_property_370812363.png" mode="s,e" name="resultLocation" refid="_16_9_299014c_1289973420703_620958_2279"/><documentation humanName="Documentation"/><ownedElement humanName="Owned Element"><instancevalue classType="InstanceValue" humanType="Instance Value" icon="MTConnect SysML Model_files/icon_instancevalue_1120275690.png" name="XArm7" refid="_19_0_3_68e0225_1612555979835_367914_44653" text="XArm7"/></ownedElement><owner classType="InstanceSpecification" humanName="Owner" humanType="Instance Specification" icon="MTConnect SysML Model_files/icon_instancespecification_1004219512.png" mode="s,e" name=" : SimulationProfile::config::SimulationConfig" refid="_19_0_3_91b028d_1582231388420_483204_48"/><owningInstance classType="InstanceSpecification" humanName="Owning Instance" humanType="Instance Specification" icon="MTConnect SysML Model_files/icon_instancespecification_1004219512.png" name=" : SimulationProfile::config::SimulationConfig" refid="_19_0_3_91b028d_1582231388420_483204_48"/><TO_DO humanName="To Do" mode="s,e"/><value humanName="Value" mode="s,e"><instancevalue classType="InstanceValue" humanType="Instance Value" icon="MTConnect SysML Model_files/icon_instancevalue_1120275690.png" name="XArm7" refid="_19_0_3_68e0225_1612555979835_367914_44653" text="XArm7"/></value></slot></magicdraw>