<?xml version="1.0" encoding="UTF-8"?><magicdraw><enumerationliteral classType="EnumerationLiteral" humanType="Enumeration Literal" icon="MTConnect SysML Model_files/icon_enumerationliteral_603852487.png" id="_19_0_3_68e0225_1605550291836_389354_1947"><classifier humanName="Classifier"><valuetype classType="Enumeration" humanType="Value Type" icon="MTConnect SysML Model_files/icon_valuetype_1348593479.png" name="ProcessStateEnum" refid="_19_0_3_68e0225_1605550283222_680737_1925"/></classifier><documentation humanName="Documentation" mode="standard">This is a raw material process occurrence, prior to active execution or preparation of raw material for processing.</documentation><enumeration classType="Enumeration" humanName="Enumeration" humanType="Value Type" icon="MTConnect SysML Model_files/icon_valuetype_1348593479.png" name="ProcessStateEnum" refid="_19_0_3_68e0225_1605550283222_680737_1925"/><name humanName="Name" mode="s,e">RAW</name><namespace classType="Enumeration" humanName="Namespace" humanType="Value Type" icon="MTConnect SysML Model_files/icon_valuetype_1348593479.png" name="ProcessStateEnum" refid="_19_0_3_68e0225_1605550283222_680737_1925"/><ownedComment humanName="Owned Comment"><comment classType="Comment" humanType="Comment" icon="MTConnect SysML Model_files/icon_comment_1780197374.png" refid="_19_0_3_68e0225_1605550500608_819290_1973"/></ownedComment><ownedElement humanName="Owned Element"><comment classType="Comment" humanType="Comment" icon="MTConnect SysML Model_files/icon_comment_1780197374.png" refid="_19_0_3_68e0225_1605550500608_819290_1973"/></ownedElement><owner classType="Enumeration" humanName="Owner" humanType="Value Type" icon="MTConnect SysML Model_files/icon_valuetype_1348593479.png" mode="s,e" name="ProcessStateEnum" refid="_19_0_3_68e0225_1605550283222_680737_1925"/><qualifiedName humanName="Qualified Name" mode="e">Observations::Observation Types::Event Types::ProcessStateEnum::RAW</qualifiedName><TO_DO humanName="To Do" mode="s,e"/><visibility humanName="Visibility" mode="s,e">public</visibility><appearsIn><diagram classType="Diagram" humanType="Diagram" icon="MTConnect SysML Model_files/icon_SysML Block Definition Diagram_783947924.png" name="EventTypes" refid="_19_0_3_45f01b9_1580381890185_538479_5666"/></appearsIn></enumerationliteral></magicdraw>