<?xml version="1.0" encoding="UTF-8"?><magicdraw><literalstring classType="LiteralString" humanType="Literal String" icon="MTConnect SysML Model_files/icon_literalstring_309566170.png" id="_19_0_3_45f01b9_1580379055657_910428_5028"><documentation humanName="Documentation"/><name humanName="Name"/><owner classType="Property" humanName="Owner" humanType="Value Property" icon="MTConnect SysML Model_files/icon_valueproperty_903501970.png" mode="e" name="subType" refid="_19_0_3_45f01b9_1580378560587_261590_3652"/><owningProperty classType="Property" humanName="Owning Property" humanType="Value Property" icon="MTConnect SysML Model_files/icon_valueproperty_903501970.png" name="subType" refid="_19_0_3_45f01b9_1580378560587_261590_3652"/><qualifiedName humanName="Qualified Name">Observations::Observation Types::Event Types::RemainingPartCount::subType::</qualifiedName><text humanName="Text" mode="standard">REMAINING</text><TO_DO humanName="To Do"/><TYPE_MODIFIER humanName="Type Modifier"/><value humanName="Value" mode="s,e">REMAINING</value><visibility humanName="Visibility">public</visibility></literalstring></magicdraw>