<?xml version="1.0" encoding="UTF-8"?><magicdraw><class classType="Class" humanType="Class" icon="MTConnect SysML Model_files/icon_class_2034046523.png" id="_19_0_3_45f01b9_1580561174713_545054_15350"><allGeneralClassifiers humanName="All General Classifiers"><class classType="Class" humanType="Class" icon="MTConnect SysML Model_files/icon_class_2034046523.png" name="MTConnect Response Document" refid="_19_0_3_45f01b9_1580561174738_185044_15392"/><class classType="Class" humanType="Class" icon="MTConnect SysML Model_files/icon_class_2034046523.png" name="MTConnect XML Document" refid="_19_0_3_45f01b9_1580561892877_257119_16985"/><class classType="Class" humanType="Class" icon="MTConnect SysML Model_files/icon_class_2034046523.png" name="MTConnectAssets Response Document" refid="_19_0_3_45f01b9_1580561892878_583554_16987"/><class classType="Class" humanType="Class" icon="MTConnect SysML Model_files/icon_class_2034046523.png" name="Response Document" refid="_19_0_3_45f01b9_1580561892896_580901_17021"/></allGeneralClassifiers><derivedExplanation humanName="Derived Explanation"/><documentation humanName="Documentation" mode="standard">See {term:MTConnectAssets Response Document}</documentation><effectiveIRI humanName="Effective IRI">#AssetResponseDocument</effectiveIRI><generalization humanName="Generalization"><generalization classType="Generalization" humanType="Generalization" icon="MTConnect SysML Model_files/icon_generalization_779179975.png" isRelationship="true" refid="_19_0_3_45f01b9_1580562359991_603380_21412"/><generalization classType="Generalization" humanType="Generalization" icon="MTConnect SysML Model_files/icon_generalization_1305303339.png" isRelationship="true" refid="_19_0_3_45f01b9_1580575873156_627246_1774"/></generalization><isAbstract humanName="Is Abstract" mode="s,e">false</isAbstract><isActive humanName="Is Active" mode="s,e">false</isActive><isFinalSpecialization humanName="Is Final Specialization" mode="e">false</isFinalSpecialization><isLeaf humanName="Is Leaf" mode="e">false</isLeaf><name humanName="Name" mode="s,e">Asset Response Document</name><namespace classType="Package" humanName="Namespace" humanType="Package" icon="MTConnect SysML Model_files/icon_package_879292014.png" name="Glossary" refid="_19_0_3_45f01b9_1580560963999_142717_15271"/><ownedComment humanName="Owned Comment"><comment classType="Comment" humanType="Comment" icon="MTConnect SysML Model_files/icon_comment_1780197374.png" refid="_19_0_3_45f01b9_1580561174714_145722_15351"/></ownedComment><ownedElement humanName="Owned Element"><generalization classType="Generalization" humanType="Generalization" icon="MTConnect SysML Model_files/icon_generalization_779179975.png" isRelationship="true" refid="_19_0_3_45f01b9_1580562359991_603380_21412"/><generalization classType="Generalization" humanType="Generalization" icon="MTConnect SysML Model_files/icon_generalization_1305303339.png" isRelationship="true" refid="_19_0_3_45f01b9_1580575873156_627246_1774"/><comment classType="Comment" humanType="Comment" icon="MTConnect SysML Model_files/icon_comment_1780197374.png" refid="_19_0_3_45f01b9_1580561174714_145722_15351"/></ownedElement><owner classType="Package" humanName="Owner" humanType="Package" icon="MTConnect SysML Model_files/icon_package_879292014.png" mode="s,e" name="Glossary" refid="_19_0_3_45f01b9_1580560963999_142717_15271"/><owningPackage classType="Package" humanName="Owning Package" humanType="Package" icon="MTConnect SysML Model_files/icon_package_879292014.png" name="Glossary" refid="_19_0_3_45f01b9_1580560963999_142717_15271"/><package classType="Package" humanName="Package" humanType="Package" icon="MTConnect SysML Model_files/icon_package_879292014.png" name="Glossary" refid="_19_0_3_45f01b9_1580560963999_142717_15271"/><qualifiedName humanName="Qualified Name" mode="e">Glossary::Asset Response Document</qualifiedName><superClass humanName="Super Class"><class classType="Class" humanType="Class" icon="MTConnect SysML Model_files/icon_class_2034046523.png" name="MTConnectAssets Response Document" refid="_19_0_3_45f01b9_1580561892878_583554_16987"/><class classType="Class" humanType="Class" icon="MTConnect SysML Model_files/icon_class_2034046523.png" name="Response Document" refid="_19_0_3_45f01b9_1580561892896_580901_17021"/></superClass><TO_DO humanName="To Do" mode="s,e"/><visibility humanName="Visibility" mode="e">public</visibility><appearsIn><diagram classType="Diagram" humanType="Diagram" icon="MTConnect SysML Model_files/icon_Concept Modeling Diagram_502125596.png" name="Glossary" refid="_19_0_3_45f01b9_1580561008381_914370_15272"/></appearsIn></class></magicdraw>