<?xml version="1.0" encoding="UTF-8"?><magicdraw><literalinteger classType="LiteralInteger" humanType="Literal Integer" icon="MTConnect SysML Model_files/icon_literalinteger_2131915493.png" id="_19_0_3_45f01b9_1580315939529_665645_47230"><documentation humanName="Documentation"/><name humanName="Name"/><owner classType="Property" humanName="Owner" humanType="Part Property" icon="MTConnect SysML Model_files/icon_partproperty_735024539.png" mode="e" name="hasSpecification" refid="_19_0_3_45f01b9_1580315915773_473805_47210"/><owningLower classType="Property" humanName="Owning Lower" humanType="Part Property" icon="MTConnect SysML Model_files/icon_partproperty_735024539.png" name="hasSpecification" refid="_19_0_3_45f01b9_1580315915773_473805_47210"/><qualifiedName humanName="Qualified Name">Configuration::Specifications::Specifications::hasSpecification::</qualifiedName><text humanName="Text" mode="standard">1</text><TO_DO humanName="To Do"/><TYPE_MODIFIER humanName="Type Modifier"/><value humanName="Value" mode="s,e">1</value><visibility humanName="Visibility">public</visibility></literalinteger></magicdraw>