<?xml version="1.0" encoding="UTF-8"?><magicdraw><literalinteger classType="LiteralInteger" humanType="Literal Integer" icon="MTConnect SysML Model_files/icon_literalinteger_1890647049.png" id="_19_0_3_45f01b9_1581814824537_802590_5414"><documentation humanName="Documentation"/><name humanName="Name"/><owner classType="Property" humanName="Owner" humanType="Property" icon="MTConnect SysML Model_files/icon_property_1633369237.png" mode="e" name="result" refid="_19_0_3_45f01b9_1581814824530_489964_5413"/><owningLower classType="Property" humanName="Owning Lower" humanType="Property" icon="MTConnect SysML Model_files/icon_property_1633369237.png" name="result" refid="_19_0_3_45f01b9_1581814824530_489964_5413"/><qualifiedName humanName="Qualified Name">MTConnect::Sample::result::</qualifiedName><text humanName="Text" mode="standard">0</text><TO_DO humanName="To Do"/><TYPE_MODIFIER humanName="Type Modifier"/><value humanName="Value" mode="s,e">0</value><visibility humanName="Visibility">public</visibility></literalinteger></magicdraw>