<?xml version="1.0" encoding="UTF-8"?><magicdraw><association classType="Association" humanType="Association" icon="MTConnect SysML Model_files/icon_association_193012616.png" id="_19_0_3_45f01b9_1587596366617_692170_805"><documentation humanName="Documentation"/><endType humanName="End Type"><block classType="Class" humanType="Block" icon="MTConnect SysML Model_files/icon_block_1907107259.png" name="Scale" refid="_19_0_3_45f01b9_1587596359868_51018_760"/><block classType="Class" humanType="Block" icon="MTConnect SysML Model_files/icon_block_1907107259.png" name="SolidModel" refid="_19_0_3_45f01b9_1587596157073_106480_480"/></endType><feature humanName="Feature"><referenceproperty classType="Property" humanType="Reference Property" icon="MTConnect SysML Model_files/icon_referenceproperty_512818888.png" name=" : Configuration::SolidModel::SolidModel" refid="_19_0_3_45f01b9_1587596366618_448948_807"/></feature><isAbstract humanName="Is Abstract" mode="s,e">false</isAbstract><isDerived humanName="Is Derived" mode="e">false</isDerived><isFinalSpecialization humanName="Is Final Specialization">false</isFinalSpecialization><isLeaf humanName="Is Leaf">false</isLeaf><member humanName="Member"><referenceproperty classType="Property" humanType="Reference Property" icon="MTConnect SysML Model_files/icon_referenceproperty_512818888.png" name=" : Configuration::SolidModel::SolidModel" refid="_19_0_3_45f01b9_1587596366618_448948_807"/><partproperty classType="Property" humanType="Part Property" icon="MTConnect SysML Model_files/icon_partproperty_2028857691.png" name="hasScale" refid="_19_0_3_45f01b9_1587596366617_434199_806"/></member><memberEnd humanName="Member End"><referenceproperty classType="Property" humanType="Reference Property" icon="MTConnect SysML Model_files/icon_referenceproperty_512818888.png" name=" : Configuration::SolidModel::SolidModel" refid="_19_0_3_45f01b9_1587596366618_448948_807"/><partproperty classType="Property" humanType="Part Property" icon="MTConnect SysML Model_files/icon_partproperty_2028857691.png" name="hasScale" refid="_19_0_3_45f01b9_1587596366617_434199_806"/></memberEnd><name humanName="Name" mode="s,e">Scale</name><namespace classType="Package" humanName="Namespace" humanType="Package" icon="MTConnect SysML Model_files/icon_package_879292014.png" name="SolidModel" refid="_19_0_3_45f01b9_1587596036608_721900_298"/><ownedElement humanName="Owned Element"><referenceproperty classType="Property" humanType="Reference Property" icon="MTConnect SysML Model_files/icon_referenceproperty_512818888.png" name=" : Configuration::SolidModel::SolidModel" refid="_19_0_3_45f01b9_1587596366618_448948_807"/></ownedElement><ownedEnd humanName="Owned End"><referenceproperty classType="Property" humanType="Reference Property" icon="MTConnect SysML Model_files/icon_referenceproperty_512818888.png" name=" : Configuration::SolidModel::SolidModel" refid="_19_0_3_45f01b9_1587596366618_448948_807"/></ownedEnd><ownedMember humanName="Owned Member"><referenceproperty classType="Property" humanType="Reference Property" icon="MTConnect SysML Model_files/icon_referenceproperty_512818888.png" name=" : Configuration::SolidModel::SolidModel" refid="_19_0_3_45f01b9_1587596366618_448948_807"/></ownedMember><owner classType="Package" humanName="Owner" humanType="Package" icon="MTConnect SysML Model_files/icon_package_879292014.png" mode="s,e" name="SolidModel" refid="_19_0_3_45f01b9_1587596036608_721900_298"/><owningPackage classType="Package" humanName="Owning Package" humanType="Package" icon="MTConnect SysML Model_files/icon_package_879292014.png" name="SolidModel" refid="_19_0_3_45f01b9_1587596036608_721900_298"/><package classType="Package" humanName="Package" humanType="Package" icon="MTConnect SysML Model_files/icon_package_879292014.png" name="SolidModel" refid="_19_0_3_45f01b9_1587596036608_721900_298"/><qualifiedName humanName="Qualified Name" mode="e">Configuration::SolidModel::Scale</qualifiedName><relatedElement humanName="Related Element"><block classType="Class" humanType="Block" icon="MTConnect SysML Model_files/icon_block_1907107259.png" name="Scale" refid="_19_0_3_45f01b9_1587596359868_51018_760"/><block classType="Class" humanType="Block" icon="MTConnect SysML Model_files/icon_block_1907107259.png" name="SolidModel" refid="_19_0_3_45f01b9_1587596157073_106480_480"/></relatedElement><TO_DO humanName="To Do" mode="s,e"/><visibility humanName="Visibility" mode="s,e">public</visibility><appearsIn><diagram classType="Diagram" humanType="Diagram" icon="MTConnect SysML Model_files/icon_SysML Use Case Diagram_1507263101.png" name="SolidModel" refid="_19_0_3_45f01b9_1587596081247_489085_331"/></appearsIn></association></magicdraw>