<?xml version="1.0" encoding="UTF-8"?><magicdraw><slot classType="Slot" humanType="Slot" icon="MTConnect SysML Model_files/icon_slot_860228715.png" id="_19_0_3_91b028d_1582337707478_15201_13955"><definingFeature classType="Property" humanName="Defining Feature" humanType="Reference Property" icon="MTConnect SysML Model_files/icon_referenceproperty_145487278.png" mode="s,e" name="rotationVector" refid="_19_0_3_91b028d_1582233041366_778653_659"/><documentation humanName="Documentation"/><ownedElement humanName="Owned Element"><instancevalue classType="InstanceValue" humanType="Instance Value" icon="MTConnect SysML Model_files/icon_instancevalue_1900548469.png" name="XArm7.joint1.rotationVector" refid="_19_0_3_91b028d_1582337707492_669107_13957" text="XArm7.joint1.rotationVector"/></ownedElement><owner classType="InstanceSpecification" humanName="Owner" humanType="Instance Specification" icon="MTConnect SysML Model_files/icon_instancespecification_1004219512.png" mode="s,e" name="XArm7.joint1" refid="_19_0_3_91b028d_1582337707332_420244_13905"/><owningInstance classType="InstanceSpecification" humanName="Owning Instance" humanType="Instance Specification" icon="MTConnect SysML Model_files/icon_instancespecification_1004219512.png" name="XArm7.joint1" refid="_19_0_3_91b028d_1582337707332_420244_13905"/><TO_DO humanName="To Do" mode="s,e"/><value humanName="Value" mode="s,e"><instancevalue classType="InstanceValue" humanType="Instance Value" icon="MTConnect SysML Model_files/icon_instancevalue_1900548469.png" name="XArm7.joint1.rotationVector" refid="_19_0_3_91b028d_1582337707492_669107_13957" text="XArm7.joint1.rotationVector"/></value></slot></magicdraw>