<?xml version="1.0" encoding="UTF-8"?><magicdraw><connectorend classType="ConnectorEnd" humanType="Connector End" icon="MTConnect SysML Model_files/icon_connectorend_484677124.png" id="_19_0_3_91b028d_1582241772384_426498_7662"><APPLIED_STEREOTYPES humanName="Applied Stereotype" mode="s,e"><stereotype classType="Stereotype" humanType="Stereotype" icon="MTConnect SysML Model_files/icon_stereotype_1169894049.png" name="NestedConnectorEnd" refid="_11_5EAPbeta_be00301_1147431307463_773225_1455"/></APPLIED_STEREOTYPES><appliedStereotype humanName="Applied Stereotype" mode="s,e"><stereotype classType="Stereotype" humanType="Stereotype" icon="MTConnect SysML Model_files/icon_stereotype_1169894049.png" name="NestedConnectorEnd" refid="_11_5EAPbeta_be00301_1147431307463_773225_1455"><property classType="Property" humanName="Base_ Connector End" humanType="Property" icon="MTConnect SysML Model_files/icon_property_604275.png" name="base_ConnectorEnd" refid="_11_5EAPbeta_be00301_1147431313222_706950_1458"/><property classType="Property" humanName="Base_ Element" humanType="Property" icon="MTConnect SysML Model_files/icon_property_604275.png" name="base_Element" refid="_10_0EAPbeta_be00301_1123081772098_411862_275"/><property classType="Property" humanName="Base_ Element" humanType="Property" icon="MTConnect SysML Model_files/icon_property_604275.png" name="base_Element" refid="_17_0_5beta_17530432_1382583873425_737094_11432"/><property classType="Property" humanName="Property Path" humanType="Property" icon="MTConnect SysML Model_files/icon_property_604275.png" name="propertyPath" refid="_11_5EAPbeta_be00301_1147431377925_245593_1615"><partproperty classType="Property" humanType="Part Property" icon="MTConnect SysML Model_files/icon_partproperty_766564539.png" name="joint4" refid="_19_0_3_91b028d_1582241373616_667827_3967"/><referenceproperty classType="Property" humanType="Reference Property" icon="MTConnect SysML Model_files/icon_referenceproperty_2121924156.png" name="parentCoordinates" refid="_19_0_3_91b028d_1582233032304_271159_627"/></property></stereotype></appliedStereotype><appliedStereotypeInstance classType="InstanceSpecification" humanName="Applied Stereotype Instance" humanType="Instance Specification" icon="MTConnect SysML Model_files/icon_instancespecification_1004219512.png" name=" : SysML::Blocks::NestedConnectorEnd" refid="_19_0_3_91b028d_1582241772440_268956_7670"/><documentation humanName="Documentation"/><isOrdered humanName="Is Ordered">false</isOrdered><isUnique humanName="Is Unique">true</isUnique><lower humanName="Lower">1</lower><multiplicity humanName="Multiplicity" mode="s,e"/><multiplicity humanName="Multiplicity" mode="s,e"/><ownedElement humanName="Owned Element"><instancespecification classType="InstanceSpecification" humanType="Instance Specification" icon="MTConnect SysML Model_files/icon_instancespecification_1004219512.png" name=" : SysML::Blocks::NestedConnectorEnd" refid="_19_0_3_91b028d_1582241772440_268956_7670"/></ownedElement><owner classType="Connector" humanName="Owner" humanType="Binding Connector" icon="MTConnect SysML Model_files/icon_bindingconnector_1282981404.png" isRelationship="true" mode="s,e" name="Binding Connector[joint3.origin.c - joint4.parentCoordinates.c]" refid="_19_0_3_91b028d_1582241772383_921637_7660"/><role classType="Property" humanName="Role" humanType="Value Property" icon="MTConnect SysML Model_files/icon_valueproperty_1495234223.png" mode="s,e" name="c" refid="_19_0_3_91b028d_1582232821318_906545_452"/><TO_DO humanName="To Do" mode="s,e"/><upper humanName="Upper">1</upper><appearsIn><diagram classType="Diagram" humanType="Diagram" icon="MTConnect SysML Model_files/icon_SysML Parametric Diagram_1808934569.png" name="robot7axes" refid="_19_0_3_91b028d_1582241426140_218631_3979"/></appearsIn></connectorend></magicdraw>