<?xml version="1.0" encoding="UTF-8"?><magicdraw><trigger classType="Trigger" humanType="Trigger" icon="MTConnect SysML Model_files/icon_trigger_463026395.png" id="_19_0_3_91b028d_1579551646140_983856_4482"><documentation humanName="Documentation"/><event classType="SignalEvent" humanName="Event" humanType="Signal Event" icon="MTConnect SysML Model_files/icon_signalevent_1780328356.png" name="SignalEvent ACTIVE" refid="_19_0_3_91b028d_1579551646139_764054_4481"/><eventType humanName="Event Type" mode="s,e">SignalEvent</eventType><name humanName="Name" mode="s,e"/><owner classType="Transition" humanName="Owner" humanType="Transition" icon="MTConnect SysML Model_files/icon_transition_709091500.png" isRelationship="true" mode="s,e" name="Transition:ACTIVE[Simulation::Interfaces::Interface::Response::States::READY -&gt; Simulation::Interfaces::Interface::Response::States::ACTIVE]" refid="_19_0_3_91b028d_1579550816624_791824_4363"/><qualifiedName humanName="Qualified Name">Simulation::Interfaces::Interface::Response::States::::</qualifiedName><TO_DO humanName="To Do"/><visibility humanName="Visibility">public</visibility></trigger></magicdraw>