<?xml version="1.0" encoding="UTF-8"?><magicdraw><literalunlimitednatural classType="LiteralUnlimitedNatural" humanType="Literal Unlimited Natural" icon="MTConnect SysML Model_files/icon_literalunlimitednatural_82005798.png" id="_19_0_3_91b028d_1579539444025_367200_10021"><documentation humanName="Documentation"/><name humanName="Name"/><owner classType="Property" humanName="Owner" humanType="Value Property" icon="MTConnect SysML Model_files/icon_valueproperty_1262200577.png" mode="e" name="ProgramToolGroup" refid="EAID_2B460A0A_FFAD_4bfd_8CFE_5C173FB4CC88"/><owningUpper classType="Property" humanName="Owning Upper" humanType="Value Property" icon="MTConnect SysML Model_files/icon_valueproperty_1262200577.png" name="ProgramToolGroup" refid="EAID_2B460A0A_FFAD_4bfd_8CFE_5C173FB4CC88"/><qualifiedName humanName="Qualified Name">Assets::CuttingTool::CuttingItem::CuttingItem::ProgramToolGroup::</qualifiedName><text humanName="Text" mode="standard">1</text><TO_DO humanName="To Do"/><TYPE_MODIFIER humanName="Type Modifier"/><value humanName="Value" mode="s,e">1</value><visibility humanName="Visibility">public</visibility></literalunlimitednatural></magicdraw>