<?xml version="1.0" encoding="UTF-8"?><magicdraw><referenceproperty classType="Property" humanType="Reference Property" icon="MTConnect SysML Model_files/icon_referenceproperty_1622419606.png" id="_19_0_3_91b028d_1579275083336_413555_3178"><aggregation humanName="Aggregation" mode="s,e">none</aggregation><APPLIED_STEREOTYPES humanName="Applied Stereotype" mode="s,e"><stereotype classType="Stereotype" humanType="Stereotype" icon="MTConnect SysML Model_files/icon_stereotype_1622419606.png" name="ReferenceProperty" refid="_15_0_be00301_1199378032543_992832_3096"/></APPLIED_STEREOTYPES><appliedStereotype humanName="Applied Stereotype" mode="s,e"><stereotype classType="Stereotype" humanType="Stereotype" icon="MTConnect SysML Model_files/icon_stereotype_1622419606.png" name="ReferenceProperty" refid="_15_0_be00301_1199378032543_992832_3096"><property classType="Property" humanName="Base_ Element" humanType="Property" icon="MTConnect SysML Model_files/icon_property_370812363.png" name="base_Element" refid="_10_0EAPbeta_be00301_1123081772098_411862_275"/><property classType="Property" humanName="Base_ Property" humanType="Property" icon="MTConnect SysML Model_files/icon_property_370812363.png" name="base_Property" refid="_15_0_be00301_1199377823726_427483_2897"/><property classType="Property" humanName="Base_ Property" humanType="Property" icon="MTConnect SysML Model_files/icon_property_370812363.png" name="base_Property" refid="_11_5EAPbeta_be00301_1147424449672_715796_1055"/><property classType="Property" humanName="Base_ Property" humanType="Property" icon="MTConnect SysML Model_files/icon_property_370812363.png" name="base_Property" refid="_15_0_be00301_1199378034525_138530_3099"/></stereotype></appliedStereotype><appliedStereotypeInstance classType="InstanceSpecification" humanName="Applied Stereotype Instance" humanType="Instance Specification" icon="MTConnect SysML Model_files/icon_instancespecification_1004219512.png" name=" : MD Customization for SysML::additional_stereotypes::ReferenceProperty" refid="_19_0_3_91b028d_1579275328273_187277_3289"/><association classType="Association" humanName="Association" humanType="Association" icon="MTConnect SysML Model_files/icon_association_2005074886.png" isRelationship="true" name="Configuration" refid="_19_0_3_91b028d_1579275083336_401152_3176"/><UMLClass classType="Class" humanName="Class" humanType="Block" icon="MTConnect SysML Model_files/icon_block_1253961629.png" name="Configuration" refid="EAID_C04DCC77_16E8_4cef_92D4_B777AFC52570"/><classifier classType="Class" humanName="Classifier" humanType="Block" icon="MTConnect SysML Model_files/icon_block_1253961629.png" name="Configuration" refid="EAID_C04DCC77_16E8_4cef_92D4_B777AFC52570"/><documentation humanName="Documentation"/><effectiveIRI humanName="Effective IRI"/><featuringClassifier classType="Class" humanName="Featuring Classifier" humanType="Block" icon="MTConnect SysML Model_files/icon_block_1253961629.png" name="Configuration" refid="EAID_C04DCC77_16E8_4cef_92D4_B777AFC52570"/><isComposite humanName="Is Composite">false</isComposite><isDerived humanName="Is Derived" mode="s,e">false</isDerived><isDerivedUnion humanName="Is Derived Union" mode="e">false</isDerivedUnion><isID humanName="Is ID" mode="e">false</isID><isLeaf humanName="Is Leaf">false</isLeaf><isOrdered humanName="Is Ordered" mode="e">false</isOrdered><isReadOnly humanName="Is Read Only" mode="s,e">false</isReadOnly><isStatic humanName="Is Static" mode="s,e">false</isStatic><isUnique humanName="Is Unique" mode="e">true</isUnique><lower humanName="Lower">1</lower><multiplicity humanName="Multiplicity" mode="s,e"/><multiplicity humanName="Multiplicity" mode="s,e"/><name humanName="Name" mode="s,e">isConfigurationFor</name><namespace classType="Class" humanName="Namespace" humanType="Block" icon="MTConnect SysML Model_files/icon_block_1253961629.png" name="Configuration" refid="EAID_C04DCC77_16E8_4cef_92D4_B777AFC52570"/><navigable humanName="Navigable" mode="e">true</navigable><opposite classType="Property" humanName="Opposite" humanType="Part Property" icon="MTConnect SysML Model_files/icon_partproperty_248094467.png" name="hasConfiguration" refid="_19_0_3_91b028d_1579275083336_877816_3177"/><ownedBy classType="Class" humanName="Owned By" humanType="Block" icon="MTConnect SysML Model_files/icon_block_1253961629.png" mode="s,e" name="Configuration" refid="EAID_C04DCC77_16E8_4cef_92D4_B777AFC52570"/><ownedElement humanName="Owned Element"><instancespecification classType="InstanceSpecification" humanType="Instance Specification" icon="MTConnect SysML Model_files/icon_instancespecification_1004219512.png" name=" : MD Customization for SysML::additional_stereotypes::ReferenceProperty" refid="_19_0_3_91b028d_1579275328273_187277_3289"/></ownedElement><owner classType="Class" humanName="Owner" humanType="Block" icon="MTConnect SysML Model_files/icon_block_1253961629.png" name="Configuration" refid="EAID_C04DCC77_16E8_4cef_92D4_B777AFC52570"/><qualifiedName humanName="Qualified Name" mode="e">Configuration::Configuration::isConfigurationFor</qualifiedName><redefinitionContext humanName="Redefinition Context"><block classType="Class" humanType="Block" icon="MTConnect SysML Model_files/icon_block_1253961629.png" name="Configuration" refid="EAID_C04DCC77_16E8_4cef_92D4_B777AFC52570"/></redefinitionContext><TO_DO humanName="To Do" mode="s,e"/><type classType="Class" humanName="Type" humanType="Block" icon="MTConnect SysML Model_files/icon_block_1253961629.png" mode="s,e" name="Component" refid="EAID_8548C620_467A_4f50_9A22_58D84B7E8779"/><TYPE_MODIFIER humanName="Type Modifier" mode="e"/><upper humanName="Upper">1</upper><visibility humanName="Visibility" mode="s,e">private</visibility><appearsIn><diagram classType="Diagram" humanType="Diagram" icon="MTConnect SysML Model_files/icon_SysML Block Definition Diagram_1615689115.png" name="Components" refid="_19_0_3_91b028d_1579271366865_490147_505"/><diagram classType="Diagram" humanType="Diagram" icon="MTConnect SysML Model_files/icon_SysML Block Definition Diagram_1615689115.png" name="Composition" refid="_19_0_3_45f01b9_1580312274451_712267_44568"/><diagram classType="Diagram" humanType="Diagram" icon="MTConnect SysML Model_files/icon_SysML Block Definition Diagram_1615689115.png" name="Specifications" refid="_19_0_3_45f01b9_1580315738423_345027_46902"/><diagram classType="Diagram" humanType="Diagram" icon="MTConnect SysML Model_files/icon_SysML Block Definition Diagram_1615689115.png" name="Relationships" refid="_19_0_3_91b028d_1579297864283_535494_6706"/><diagram classType="Diagram" humanType="Diagram" icon="MTConnect SysML Model_files/icon_SysML Block Definition Diagram_1615689115.png" name="Configuration" refid="_19_0_3_91b028d_1579301614342_185267_7282"/></appearsIn></referenceproperty></magicdraw>