<?xml version="1.0" encoding="UTF-8"?><magicdraw><referenceproperty classType="Property" humanType="Reference Property" icon="MTConnect SysML Model_files/icon_referenceproperty_895584545.png" id="_19_0_3_91b028d_1579274803419_670433_3065"><aggregation humanName="Aggregation" mode="s,e">none</aggregation><APPLIED_STEREOTYPES humanName="Applied Stereotype" mode="s,e"><stereotype classType="Stereotype" humanType="Stereotype" icon="MTConnect SysML Model_files/icon_stereotype_895584545.png" name="ReferenceProperty" refid="_15_0_be00301_1199378032543_992832_3096"/></APPLIED_STEREOTYPES><appliedStereotype humanName="Applied Stereotype" mode="s,e"><stereotype classType="Stereotype" humanType="Stereotype" icon="MTConnect SysML Model_files/icon_stereotype_895584545.png" name="ReferenceProperty" refid="_15_0_be00301_1199378032543_992832_3096"><property classType="Property" humanName="Base_ Element" humanType="Property" icon="MTConnect SysML Model_files/icon_property_604275.png" name="base_Element" refid="_10_0EAPbeta_be00301_1123081772098_411862_275"/><property classType="Property" humanName="Base_ Property" humanType="Property" icon="MTConnect SysML Model_files/icon_property_604275.png" name="base_Property" refid="_15_0_be00301_1199378034525_138530_3099"/><property classType="Property" humanName="Base_ Property" humanType="Property" icon="MTConnect SysML Model_files/icon_property_604275.png" name="base_Property" refid="_11_5EAPbeta_be00301_1147424449672_715796_1055"/><property classType="Property" humanName="Base_ Property" humanType="Property" icon="MTConnect SysML Model_files/icon_property_604275.png" name="base_Property" refid="_15_0_be00301_1199377823726_427483_2897"/></stereotype></appliedStereotype><appliedStereotypeInstance classType="InstanceSpecification" humanName="Applied Stereotype Instance" humanType="Instance Specification" icon="MTConnect SysML Model_files/icon_instancespecification_1004219512.png" name=" : MD Customization for SysML::additional_stereotypes::ReferenceProperty" refid="_19_0_3_91b028d_1579275361600_506902_3291"/><association classType="Association" humanName="Association" humanType="Association" icon="MTConnect SysML Model_files/icon_association_346544221.png" isRelationship="true" name="Compositions" refid="_19_0_3_91b028d_1579274803419_701287_3063"/><UMLClass classType="Class" humanName="Class" humanType="Block" icon="MTConnect SysML Model_files/icon_block_790094901.png" name="Composition" refid="EAID_C2A7EE38_2DE9_4a7e_B674_0EC719977860"/><classifier classType="Class" humanName="Classifier" humanType="Block" icon="MTConnect SysML Model_files/icon_block_790094901.png" name="Composition" refid="EAID_C2A7EE38_2DE9_4a7e_B674_0EC719977860"/><documentation humanName="Documentation"/><effectiveIRI humanName="Effective IRI"/><featuringClassifier classType="Class" humanName="Featuring Classifier" humanType="Block" icon="MTConnect SysML Model_files/icon_block_790094901.png" name="Composition" refid="EAID_C2A7EE38_2DE9_4a7e_B674_0EC719977860"/><isComposite humanName="Is Composite">false</isComposite><isDerived humanName="Is Derived" mode="s,e">false</isDerived><isDerivedUnion humanName="Is Derived Union" mode="e">false</isDerivedUnion><isID humanName="Is ID" mode="e">false</isID><isLeaf humanName="Is Leaf">false</isLeaf><isOrdered humanName="Is Ordered" mode="e">false</isOrdered><isReadOnly humanName="Is Read Only" mode="s,e">false</isReadOnly><isStatic humanName="Is Static" mode="s,e">false</isStatic><isUnique humanName="Is Unique" mode="e">true</isUnique><lower humanName="Lower">1</lower><multiplicity humanName="Multiplicity" mode="s,e"/><multiplicity humanName="Multiplicity" mode="s,e"/><name humanName="Name" mode="s,e">isCompositionOf</name><namespace classType="Class" humanName="Namespace" humanType="Block" icon="MTConnect SysML Model_files/icon_block_790094901.png" name="Composition" refid="EAID_C2A7EE38_2DE9_4a7e_B674_0EC719977860"/><navigable humanName="Navigable" mode="e">true</navigable><opposite classType="Property" humanName="Opposite" humanType="Part Property" icon="MTConnect SysML Model_files/icon_partproperty_1918091595.png" name="hasComposition" refid="_19_0_3_91b028d_1579274803419_180043_3064"/><ownedBy classType="Class" humanName="Owned By" humanType="Block" icon="MTConnect SysML Model_files/icon_block_790094901.png" mode="s,e" name="Composition" refid="EAID_C2A7EE38_2DE9_4a7e_B674_0EC719977860"/><ownedElement humanName="Owned Element"><instancespecification classType="InstanceSpecification" humanType="Instance Specification" icon="MTConnect SysML Model_files/icon_instancespecification_1004219512.png" name=" : MD Customization for SysML::additional_stereotypes::ReferenceProperty" refid="_19_0_3_91b028d_1579275361600_506902_3291"/></ownedElement><owner classType="Class" humanName="Owner" humanType="Block" icon="MTConnect SysML Model_files/icon_block_790094901.png" name="Composition" refid="EAID_C2A7EE38_2DE9_4a7e_B674_0EC719977860"/><qualifiedName humanName="Qualified Name" mode="e">Compositions::Composition::isCompositionOf</qualifiedName><redefinitionContext humanName="Redefinition Context"><block classType="Class" humanType="Block" icon="MTConnect SysML Model_files/icon_block_790094901.png" name="Composition" refid="EAID_C2A7EE38_2DE9_4a7e_B674_0EC719977860"/></redefinitionContext><TO_DO humanName="To Do" mode="s,e"/><type classType="Class" humanName="Type" humanType="Block" icon="MTConnect SysML Model_files/icon_block_790094901.png" mode="s,e" name="Component" refid="EAID_8548C620_467A_4f50_9A22_58D84B7E8779"/><TYPE_MODIFIER humanName="Type Modifier" mode="e"/><upper humanName="Upper">1</upper><visibility humanName="Visibility" mode="s,e">private</visibility><appearsIn><diagram classType="Diagram" humanType="Diagram" icon="MTConnect SysML Model_files/icon_SysML Block Definition Diagram_988480626.png" name="Composition" refid="_19_0_3_45f01b9_1580312274451_712267_44568"/><diagram classType="Diagram" humanType="Diagram" icon="MTConnect SysML Model_files/icon_SysML Block Definition Diagram_988480626.png" name="CompositionTypes" refid="_19_0_3_45f01b9_1580312764124_506709_44885"/><diagram classType="Diagram" humanType="Diagram" icon="MTConnect SysML Model_files/icon_SysML Block Definition Diagram_988480626.png" name="Components" refid="_19_0_3_91b028d_1579271366865_490147_505"/></appearsIn></referenceproperty></magicdraw>