<?xml version="1.0" encoding="UTF-8"?><magicdraw><block classType="AssociationClass" humanType="Block" icon="MTConnect SysML Model_files/icon_block_907521510.png" id="EAID_657167D1_2EA5_4095_88EC_49E69674A734"><APPLIED_STEREOTYPES humanName="Applied Stereotype" mode="s,e"><stereotype classType="Stereotype" humanType="Stereotype" icon="MTConnect SysML Model_files/icon_stereotype_907521510.png" name="Block" refid="_11_5EAPbeta_be00301_1147424179914_458922_958"/></APPLIED_STEREOTYPES><appliedStereotype humanName="Applied Stereotype" mode="s,e"><stereotype classType="Stereotype" humanType="Stereotype" icon="MTConnect SysML Model_files/icon_stereotype_907521510.png" name="Block" refid="_11_5EAPbeta_be00301_1147424179914_458922_958"><property classType="Property" humanName="Base_ Class" humanType="Property" icon="MTConnect SysML Model_files/icon_property_1366743023.png" name="base_Class" refid="_11_5EAPbeta_be00301_1147424181797_326831_961"/><property classType="Property" humanName="Is Encapsulated" humanType="Property" icon="MTConnect SysML Model_files/icon_property_1366743023.png" name="isEncapsulated" refid="_11_5EAPbeta_be00301_1147424201876_860708_1049"/></stereotype></appliedStereotype><appliedStereotypeInstance classType="InstanceSpecification" humanName="Applied Stereotype Instance" humanType="Instance Specification" icon="MTConnect SysML Model_files/icon_instancespecification_1004219512.png" name=" : SysML::Blocks::Block" refid="_19_0_3_91b028d_1579537925762_943143_9890"/><attribute humanName="Attribute"><partproperty classType="Property" humanType="Part Property" icon="MTConnect SysML Model_files/icon_partproperty_1698394758.png" name=" : Assets::CuttingTool::CuttingItem::CuttingItem [0..*]" refid="EAID_DED5A27A_9C95_4f51_8048_F412C4D56E92"/><partproperty classType="Property" humanType="Part Property" icon="MTConnect SysML Model_files/icon_partproperty_1698394758.png" name=" : Assets::CuttingTool::CuttingToolLifeCycle::CuttingToolLifeCycle" refid="EAID_327E7BCB_39EE_4bc1_A658_07ABBCDC66A8"/><valueproperty classType="Property" humanType="Value Property" icon="MTConnect SysML Model_files/icon_valueproperty_444146789.png" name="count" refid="EAID_516F68EB_58C5_4642_837C_FEA26B29A7F9"/></attribute><derivedExplanation humanName="Derived Explanation"/><documentation humanName="Documentation" mode="standard">{{block(CuttingItems)}} {{termplural(organize)}} {{block(CuttingItem)}} elements.</documentation><effectiveIRI humanName="Effective IRI"/><endType humanName="End Type"><block classType="Class" humanType="Block" icon="MTConnect SysML Model_files/icon_block_907521510.png" name="CuttingItem" refid="EAID_99183806_F570_4387_BA6D_34929C20F954"/><block classType="Class" humanType="Block" icon="MTConnect SysML Model_files/icon_block_907521510.png" name="CuttingToolLifeCycle" refid="EAID_D1C82EBD_D828_4e5f_9F46_3337710837FE"/></endType><feature humanName="Feature"><partproperty classType="Property" humanType="Part Property" icon="MTConnect SysML Model_files/icon_partproperty_1698394758.png" name=" : Assets::CuttingTool::CuttingItem::CuttingItem [0..*]" refid="EAID_DED5A27A_9C95_4f51_8048_F412C4D56E92"/><property classType="Property" humanType="Property" icon="MTConnect SysML Model_files/icon_property_1366743023.png" name=" : Assets::CuttingTool::CuttingToolLifeCycle::CuttingToolLifeCycle" refid="EAID_srcAB92D5_E33E_4e6e_92EB_1FFFBF29ED9F"/><partproperty classType="Property" humanType="Part Property" icon="MTConnect SysML Model_files/icon_partproperty_1698394758.png" name=" : Assets::CuttingTool::CuttingToolLifeCycle::CuttingToolLifeCycle" refid="EAID_327E7BCB_39EE_4bc1_A658_07ABBCDC66A8"/><valueproperty classType="Property" humanType="Value Property" icon="MTConnect SysML Model_files/icon_valueproperty_444146789.png" name="count" refid="EAID_516F68EB_58C5_4642_837C_FEA26B29A7F9"/></feature><isAbstract humanName="Is Abstract">false</isAbstract><isActive humanName="Is Active" mode="e">false</isActive><isDerived humanName="Is Derived" mode="e">false</isDerived><isFinalSpecialization humanName="Is Final Specialization">false</isFinalSpecialization><isLeaf humanName="Is Leaf">false</isLeaf><member humanName="Member"><partproperty classType="Property" humanType="Part Property" icon="MTConnect SysML Model_files/icon_partproperty_1698394758.png" name=" : Assets::CuttingTool::CuttingItem::CuttingItem [0..*]" refid="EAID_DED5A27A_9C95_4f51_8048_F412C4D56E92"/><property classType="Property" humanType="Property" icon="MTConnect SysML Model_files/icon_property_1366743023.png" name=" : Assets::CuttingTool::CuttingToolLifeCycle::CuttingToolLifeCycle" refid="EAID_srcAB92D5_E33E_4e6e_92EB_1FFFBF29ED9F"/><partproperty classType="Property" humanType="Part Property" icon="MTConnect SysML Model_files/icon_partproperty_1698394758.png" name=" : Assets::CuttingTool::CuttingToolLifeCycle::CuttingToolLifeCycle" refid="EAID_327E7BCB_39EE_4bc1_A658_07ABBCDC66A8"/><valueproperty classType="Property" humanType="Value Property" icon="MTConnect SysML Model_files/icon_valueproperty_444146789.png" name="count" refid="EAID_516F68EB_58C5_4642_837C_FEA26B29A7F9"/><referenceproperty classType="Property" humanType="Reference Property" icon="MTConnect SysML Model_files/icon_referenceproperty_1801226885.png" name="hasCuttingItem" refid="EAID_dstAB92D5_E33E_4e6e_92EB_1FFFBF29ED9F"/></member><memberEnd humanName="Member End"><property classType="Property" humanType="Property" icon="MTConnect SysML Model_files/icon_property_1366743023.png" name=" : Assets::CuttingTool::CuttingToolLifeCycle::CuttingToolLifeCycle" refid="EAID_srcAB92D5_E33E_4e6e_92EB_1FFFBF29ED9F"/><referenceproperty classType="Property" humanType="Reference Property" icon="MTConnect SysML Model_files/icon_referenceproperty_1801226885.png" name="hasCuttingItem" refid="EAID_dstAB92D5_E33E_4e6e_92EB_1FFFBF29ED9F"/></memberEnd><name humanName="Name" mode="s,e">CuttingItems</name><namespace classType="Package" humanName="Namespace" humanType="Package" icon="MTConnect SysML Model_files/icon_package_1684615718.png" name="CuttingItem" refid="EAPK_2734C012_030C_44a6_8CE6_559328AFDCB9"/><ownedAttribute humanName="Owned Attribute"><partproperty classType="Property" humanType="Part Property" icon="MTConnect SysML Model_files/icon_partproperty_1698394758.png" name=" : Assets::CuttingTool::CuttingItem::CuttingItem [0..*]" refid="EAID_DED5A27A_9C95_4f51_8048_F412C4D56E92"/><partproperty classType="Property" humanType="Part Property" icon="MTConnect SysML Model_files/icon_partproperty_1698394758.png" name=" : Assets::CuttingTool::CuttingToolLifeCycle::CuttingToolLifeCycle" refid="EAID_327E7BCB_39EE_4bc1_A658_07ABBCDC66A8"/><valueproperty classType="Property" humanType="Value Property" icon="MTConnect SysML Model_files/icon_valueproperty_444146789.png" name="count" refid="EAID_516F68EB_58C5_4642_837C_FEA26B29A7F9"/></ownedAttribute><ownedComment humanName="Owned Comment"><comment classType="Comment" humanType="Comment" icon="MTConnect SysML Model_files/icon_comment_692796401.png" refid="_19_0_3_68e0225_1611659616129_311693_129"/></ownedComment><ownedElement humanName="Owned Element"><comment classType="Comment" humanType="Comment" icon="MTConnect SysML Model_files/icon_comment_692796401.png" refid="_19_0_3_68e0225_1611659616129_311693_129"/><partproperty classType="Property" humanType="Part Property" icon="MTConnect SysML Model_files/icon_partproperty_1698394758.png" name=" : Assets::CuttingTool::CuttingItem::CuttingItem [0..*]" refid="EAID_DED5A27A_9C95_4f51_8048_F412C4D56E92"/><property classType="Property" humanType="Property" icon="MTConnect SysML Model_files/icon_property_1366743023.png" name=" : Assets::CuttingTool::CuttingToolLifeCycle::CuttingToolLifeCycle" refid="EAID_srcAB92D5_E33E_4e6e_92EB_1FFFBF29ED9F"/><partproperty classType="Property" humanType="Part Property" icon="MTConnect SysML Model_files/icon_partproperty_1698394758.png" name=" : Assets::CuttingTool::CuttingToolLifeCycle::CuttingToolLifeCycle" refid="EAID_327E7BCB_39EE_4bc1_A658_07ABBCDC66A8"/><instancespecification classType="InstanceSpecification" humanType="Instance Specification" icon="MTConnect SysML Model_files/icon_instancespecification_1004219512.png" name=" : SysML::Blocks::Block" refid="_19_0_3_91b028d_1579537925762_943143_9890"/><valueproperty classType="Property" humanType="Value Property" icon="MTConnect SysML Model_files/icon_valueproperty_444146789.png" name="count" refid="EAID_516F68EB_58C5_4642_837C_FEA26B29A7F9"/></ownedElement><ownedEnd humanName="Owned End"><property classType="Property" humanType="Property" icon="MTConnect SysML Model_files/icon_property_1366743023.png" name=" : Assets::CuttingTool::CuttingToolLifeCycle::CuttingToolLifeCycle" refid="EAID_srcAB92D5_E33E_4e6e_92EB_1FFFBF29ED9F"/></ownedEnd><ownedMember humanName="Owned Member"><partproperty classType="Property" humanType="Part Property" icon="MTConnect SysML Model_files/icon_partproperty_1698394758.png" name=" : Assets::CuttingTool::CuttingItem::CuttingItem [0..*]" refid="EAID_DED5A27A_9C95_4f51_8048_F412C4D56E92"/><property classType="Property" humanType="Property" icon="MTConnect SysML Model_files/icon_property_1366743023.png" name=" : Assets::CuttingTool::CuttingToolLifeCycle::CuttingToolLifeCycle" refid="EAID_srcAB92D5_E33E_4e6e_92EB_1FFFBF29ED9F"/><partproperty classType="Property" humanType="Part Property" icon="MTConnect SysML Model_files/icon_partproperty_1698394758.png" name=" : Assets::CuttingTool::CuttingToolLifeCycle::CuttingToolLifeCycle" refid="EAID_327E7BCB_39EE_4bc1_A658_07ABBCDC66A8"/><valueproperty classType="Property" humanType="Value Property" icon="MTConnect SysML Model_files/icon_valueproperty_444146789.png" name="count" refid="EAID_516F68EB_58C5_4642_837C_FEA26B29A7F9"/></ownedMember><owner classType="Package" humanName="Owner" humanType="Package" icon="MTConnect SysML Model_files/icon_package_1684615718.png" mode="s,e" name="CuttingItem" refid="EAPK_2734C012_030C_44a6_8CE6_559328AFDCB9"/><owningPackage classType="Package" humanName="Owning Package" humanType="Package" icon="MTConnect SysML Model_files/icon_package_1684615718.png" name="CuttingItem" refid="EAPK_2734C012_030C_44a6_8CE6_559328AFDCB9"/><package classType="Package" humanName="Package" humanType="Package" icon="MTConnect SysML Model_files/icon_package_1684615718.png" name="CuttingItem" refid="EAPK_2734C012_030C_44a6_8CE6_559328AFDCB9"/><part humanName="Part"><partproperty classType="Property" humanType="Part Property" icon="MTConnect SysML Model_files/icon_partproperty_1698394758.png" name=" : Assets::CuttingTool::CuttingItem::CuttingItem [0..*]" refid="EAID_DED5A27A_9C95_4f51_8048_F412C4D56E92"/><partproperty classType="Property" humanType="Part Property" icon="MTConnect SysML Model_files/icon_partproperty_1698394758.png" name=" : Assets::CuttingTool::CuttingToolLifeCycle::CuttingToolLifeCycle" refid="EAID_327E7BCB_39EE_4bc1_A658_07ABBCDC66A8"/></part><qualifiedName humanName="Qualified Name" mode="e">Assets::CuttingTool::CuttingItem::CuttingItems</qualifiedName><relatedElement humanName="Related Element"><block classType="Class" humanType="Block" icon="MTConnect SysML Model_files/icon_block_907521510.png" name="CuttingItem" refid="EAID_99183806_F570_4387_BA6D_34929C20F954"/><block classType="Class" humanType="Block" icon="MTConnect SysML Model_files/icon_block_907521510.png" name="CuttingToolLifeCycle" refid="EAID_D1C82EBD_D828_4e5f_9F46_3337710837FE"/></relatedElement><role humanName="Role"><partproperty classType="Property" humanType="Part Property" icon="MTConnect SysML Model_files/icon_partproperty_1698394758.png" name=" : Assets::CuttingTool::CuttingItem::CuttingItem [0..*]" refid="EAID_DED5A27A_9C95_4f51_8048_F412C4D56E92"/><partproperty classType="Property" humanType="Part Property" icon="MTConnect SysML Model_files/icon_partproperty_1698394758.png" name=" : Assets::CuttingTool::CuttingToolLifeCycle::CuttingToolLifeCycle" refid="EAID_327E7BCB_39EE_4bc1_A658_07ABBCDC66A8"/><valueproperty classType="Property" humanType="Value Property" icon="MTConnect SysML Model_files/icon_valueproperty_444146789.png" name="count" refid="EAID_516F68EB_58C5_4642_837C_FEA26B29A7F9"/></role><TO_DO humanName="To Do" mode="s,e"/><visibility humanName="Visibility">public</visibility><appearsIn><diagram classType="Diagram" humanType="Diagram" icon="MTConnect SysML Model_files/icon_SysML Block Definition Diagram_2048589015.png" name="CuttingToolLifeCycle" refid="_19_0_3_91b028d_1579537675254_534658_9243"/></appearsIn></block></magicdraw>