<?xml version="1.0" encoding="UTF-8"?><magicdraw><property classType="Property" humanType="Property" icon="MTConnect SysML Model_files/icon_property_370812363.png" id="EAID_src1A4CE1_D365_43ee_B7FA_A43687E78C4E"><aggregation humanName="Aggregation" mode="s,e">none</aggregation><association classType="Association" humanName="Association" humanType="Association" icon="MTConnect SysML Model_files/icon_association_986792876.png" isRelationship="true" name="Header" refid="EAID_6D1A4CE1_D365_43ee_B7FA_A43687E78C4E"/><documentation humanName="Documentation"/><effectiveIRI humanName="Effective IRI"/><featuringClassifier classType="Association" humanName="Featuring Classifier" humanType="Association" icon="MTConnect SysML Model_files/icon_association_986792876.png" isRelationship="true" name="Header" refid="EAID_6D1A4CE1_D365_43ee_B7FA_A43687E78C4E"/><isComposite humanName="Is Composite">false</isComposite><isDerived humanName="Is Derived" mode="s,e">false</isDerived><isDerivedUnion humanName="Is Derived Union" mode="e">false</isDerivedUnion><isID humanName="Is ID" mode="e">false</isID><isLeaf humanName="Is Leaf">false</isLeaf><isOrdered humanName="Is Ordered" mode="e">false</isOrdered><isReadOnly humanName="Is Read Only" mode="s,e">false</isReadOnly><isStatic humanName="Is Static" mode="s,e">false</isStatic><isUnique humanName="Is Unique" mode="e">true</isUnique><lower humanName="Lower">1</lower><multiplicity humanName="Multiplicity" mode="s,e"/><multiplicity humanName="Multiplicity" mode="s,e"/><name humanName="Name" mode="s,e"/><namespace classType="Association" humanName="Namespace" humanType="Association" icon="MTConnect SysML Model_files/icon_association_986792876.png" isRelationship="true" name="Header" refid="EAID_6D1A4CE1_D365_43ee_B7FA_A43687E78C4E"/><navigable humanName="Navigable" mode="e">false</navigable><opposite classType="Property" humanName="Opposite" humanType="Reference Property" icon="MTConnect SysML Model_files/icon_referenceproperty_1426052444.png" name="hasHeader" refid="EAID_dst1A4CE1_D365_43ee_B7FA_A43687E78C4E"/><ownedBy classType="Association" humanName="Owned By" humanType="Association" icon="MTConnect SysML Model_files/icon_association_986792876.png" isRelationship="true" mode="s,e" name="Header" refid="EAID_6D1A4CE1_D365_43ee_B7FA_A43687E78C4E"/><owner classType="Association" humanName="Owner" humanType="Association" icon="MTConnect SysML Model_files/icon_association_986792876.png" isRelationship="true" name="Header" refid="EAID_6D1A4CE1_D365_43ee_B7FA_A43687E78C4E"/><owningAssociation classType="Association" humanName="Owning Association" humanType="Association" icon="MTConnect SysML Model_files/icon_association_986792876.png" isRelationship="true" name="Header" refid="EAID_6D1A4CE1_D365_43ee_B7FA_A43687E78C4E"/><qualifiedName humanName="Qualified Name" mode="e">Protocols::MTConnect Protocol::MTConnectStreams::Header::</qualifiedName><redefinitionContext humanName="Redefinition Context"><association classType="Association" humanType="Association" icon="MTConnect SysML Model_files/icon_association_986792876.png" isRelationship="true" name="Header" refid="EAID_6D1A4CE1_D365_43ee_B7FA_A43687E78C4E"/></redefinitionContext><TO_DO humanName="To Do" mode="s,e"/><type classType="Class" humanName="Type" humanType="Block" icon="MTConnect SysML Model_files/icon_block_1400898224.png" mode="s,e" name="MTConnectStreams" refid="EAID_156BB3E5_EB08_4e64_A874_6DDFC07D68CC"/><TYPE_MODIFIER humanName="Type Modifier" mode="e"/><upper humanName="Upper">1</upper><visibility humanName="Visibility" mode="s,e">public</visibility><appearsIn><diagram classType="Diagram" humanType="Diagram" icon="MTConnect SysML Model_files/icon_SysML Block Definition Diagram_1615689115.png" name="MTConnectStreams" refid="_19_0_3_91b028d_1579559933379_492237_5850"/></appearsIn></property></magicdraw>